Metadata-Version: 2.1
Name: wsy
Version: 1.0.0
Summary: A package for my girlfriend, wsy.
Home-page: https://github.com/Su-luoya
Author: Suluoya
Author-email: 1931960436@qq.com
Maintainer: Suluoya
Maintainer-email: 1931960436@qq.com
License: UNKNOWN
Platform: UNKNOWN
Classifier: Programming Language :: Python :: 3 :: Only
Classifier: License :: OSI Approved :: MIT License
Classifier: Operating System :: OS Independent
License-File: LICENSE
